{
    "interests": [
        {
            "label": "Frontend Development",
            "image": {
                "src": "../../images/web-dev-icon.png",
                "alt": ""
            }
        },
        {
            "label": "Backend Development",
            "image": {
                "src": "../../images/backend-development.png",
                "alt": ""
            }
        },
        {
            "label": "Fullstack Development",
            "image": {
                "src": "../../images/6674627.png",
                "alt": ""
            }
        },
        {
            "label": "Mobile Development",
            "image": {
                "src": "../../images/mobile-development.png",
                "alt": ""
            }
        },
        {
            "label": "Machine Learning",
            "image": {
                "src": "../../images/machine-learning.png",
                "alt": ""
            }
        },
        {
            "label": "Emerging Technologies",
            "image": {
                "src": "../../images/233-2339305_iot-icon-png-transparent.png",
                "alt": ""
            }
        }
    ],
    "button": {
        "visible": false,
        "label": "+ Load More",
        "initiallyShownInterests": 5
    }
}
